aws_lambda_api_event_utils/__init__.py
aws_lambda_api_event_utils/aws_lambda_api_event_utils.py
aws_lambda_api_event_utils/aws_lambda_api_event_validators.py
aws_lambda_api_event_utils/py.typed
aws_lambda_api_event_utils-0.3.0.dist-info/LICENSE
aws_lambda_api_event_utils-0.3.0.dist-info/WHEEL
aws_lambda_api_event_utils-0.3.0.dist-info/METADATA
aws_lambda_api_event_utils-0.3.0.dist-info/RECORD
