Metadata-Version: 2.1
Name: aws-lambda-api-event-utils
Version: 0.3.0
Summary: Lightweight processing of API events for AWS Lambda
Home-page: https://github.com/benkehoe/aws-lambda-api-event-utils
License: Apache-2.0
Author: Ben Kehoe
Author-email: ben@kehoe.io
Requires-Python: >=3.7,<4.0
Classifier: Development Status :: 3 - Alpha
Classifier: Intended Audience :: Developers
Classifier: Intended Audience :: System Administrators
Classifier: License :: OSI Approved :: Apache Software License
Classifier: Operating System :: OS Independent
Classifier: Programming Language :: Python :: 3
Classifier: Programming Language :: Python :: 3.10
Classifier: Programming Language :: Python :: 3.7
Classifier: Programming Language :: Python :: 3.8
Classifier: Programming Language :: Python :: 3.9
Classifier: Topic :: Utilities
Requires-Dist: fastjsonschema[fastjsonschema] (>=2.15.3,<3.0.0)
Requires-Dist: jsonschema[jsonschema] (>=4.2.1,<5.0.0)
Project-URL: Repository, https://github.com/benkehoe/aws-lambda-api-event-utils
